transform3d/__init__.py
transform3d/scene.py
transform3d/transform.py
transform3d/tests/__init__.py
transform3d/tests/test_scene.py
transform3d/tests/test_transform.py
transform3d-0.0.4.dist-info/METADATA
transform3d-0.0.4.dist-info/WHEEL
transform3d-0.0.4.dist-info/top_level.txt
transform3d-0.0.4.dist-info/RECORD
