Metadata-Version: 2.1
Name: transform3d
Version: 0.0.4
Summary: Handy classes for working with trees of 3d transformations.
Home-page: https://github.com/RasmusHaugaard/transform3d
Author: Rasmus Laurvig Haugaard
Author-email: rasmus.l.haugaard@gmail.com
License: UNKNOWN
Platform: UNKNOWN
Requires-Python: >=3.6
